Workbook

Sheet Instrucciones
A1: RETO PRÁCTICO: ANÁLISIS DE RENTABILIDAD TECH RETAIL
I2: Tasa Comisión T.C.: | J2: 0.035
A3: Objetivo: Estructurar, desnormalizar y analizar el reporte de ventas sin asistencia de fórmulas.
A5: REQUERIMIENTOS TÉCNICOS:
A6: 1. Formato y Estructura: Convierte las hojas 'Catálogo' y 'Ventas' en Tablas de Excel formales nombradas 'DimProductos' y 'FactVentas'.
A7: 2. Desnormalización: En 'FactVentas', trae 'Producto', 'Categoria', 'Costo_Unitario' y 'Precio_Lista' desde el catálogo en una sola operación de búsqueda.
A8: 3. Métricas Financieras Base:
A9: - Crea la columna 'Ingreso_Bruto' (Cantidad * Precio_Lista).
A10: - Crea la columna 'Costo_Total' (Cantidad * Costo_Unitario).
A11: 4. Deducción Operativa:
A12: - En 'FactVentas', crea la columna 'Comision_Bancaria'.
A13: - Aplica la tasa de comisión ubicada en Instrucciones!J2 (fijando la celda) ÚNICAMENTE a los pagos con 'Tarjeta de Crédito'.
A14: - Para cualquier otro método de pago, el valor debe ser 0.
A15: 5. Margen Operativo:
... A25: - Inserta un Gráfico de Columnas Agrupadas: elimina líneas de cuadrícula, oculta botones de campo y añade etiquetas de datos directas.

Sheet Catálogo
A1: ID_Producto | B1: Producto | C1: Categoria | D1: Costo_Unitario | E1: Precio_Lista
A2: T-101 | B2: Monitor Curvo 27" | C2: Monitores | D2: 2800 | E2: 4999
A3: T-102 | B3: Teclado Mecánico RGB | C3: Accesorios | D3: 650 | E3: 1350
A4: T-103 | B4: Mouse Inalámbrico Pro | C4: Accesorios | D4: 420 | E4: 899
A5: T-104 | B5: Laptop Gamer 16GB | C5: Laptops | D5: 14500 | E5: 22499
A6: T-105 | B6: Laptop Ultrabook 14" | C6: Laptops | D6: 11200 | E6: 17999
A7: T-106 | B7: Auriculares Noise Cancelling | C7: Audio | D7: 1600 | E7: 3199
A8: T-107 | B8: Micrófono USB Studio | C8: Audio | D8: 950 | E8: 1899
A9: T-108 | B9: Silla Ergonómica Pro | C9: Mobiliario | D9: 3200 | E9: 5699

Sheet Ventas
A1: ID_Ticket | B1: Fecha | C1: ID_Producto | D1: Sucursal | E1: Metodo_Pago | F1: Cantidad | G1: Producto | H1: Categoria | I1: Costo | J1: Precio de lista | K1: Ingreso Bruto | L1: Costo total | M1: Comision Bancaria | N1: Utilidad operativa | O1: Clasificacion ticket | R1: Tickets transferencia | U1: Utilidad Operativa
A2: TK-8032 | B2: 2026-08-01 | C2: T-107 | D2: Sucursal Sur | E2: Transferencia | F2: 1 | G2: {=XLOOKUP(C2,DimProductos[ID_Producto],DimProductos[[Producto]:[Precio_Lista]])} -> Micrófono USB Studio | H2: Audio | I2: 950 | J2: 1899 | K2: =F2*J2 -> 1899 | L2: =F2*I2 -> 950 | M2: =IFS(E2="Tarjeta de Crédito",J2*Instrucciones!$J$2,E2<>"Tarjeta de Crédito",0) -> 0 | N2: =K2-L2-M2 -> 949 | O2: =IF(N2>1500,"Ticket alto valor","Ticket Estandar") -> Ticket Estandar | R2: =COUNTIF(FactVentas[Metodo_Pago],"Transferencia") -> 58 | U2: =SUMIF(FactVentas[Categoria],"Laptops",FactVentas[Utilidad operativa]) -> 691883.68
A3: TK-8101 | B3: 2026-08-01 | C3: T-106 | D3: Sucursal Poniente | E3: Efectivo | F3: 1 | G3: {=XLOOKUP(C3,DimProductos[ID_Producto],DimProductos[[Producto]:[Precio_Lista]])} -> Auriculares Noise Cancelling | H3: Audio | I3: 1600 | J3: 3199 | K3: =F3*J3 -> 3199 | L3: =F3*I3 -> 1600 | M3: =IFS(E3="Tarjeta de Crédito",J3*Instrucciones!$J$2,E3<>"Tarjeta de Crédito",0) -> 0 | N3: =K3-L3-M3 -> 1599 | O3: =IF(N3>1500,"Ticket alto valor","Ticket Estandar") -> Ticket alto valor
A4: TK-8102 | B4: 2026-08-01 | C4: T-106 | D4: Sucursal Norte | E4: Tarjeta de Débito | F4: 1 | G4: {=XLOOKUP(C4,DimProductos[ID_Producto],DimProductos[[Producto]:[Precio_Lista]])} -> Auriculares Noise Cancelling | H4: Audio | I4: 1600 | J4: 3199 | K4: =F4*J4 -> 3199 | L4: =F4*I4 -> 1600 | M4: =IFS(E4="Tarjeta de Crédito",J4*Instrucciones!$J$2,E4<>"Tarjeta de Crédito",0) -> 0 | N4: =K4-L4-M4 -> 1599 | O4: =IF(N4>1500,"Ticket alto valor","Ticket Estandar") -> Ticket alto valor
A5: TK-8107 | B5: 2026-08-01 | C5: T-104 | D5: Sucursal Sur | E5: Transferencia | F5: 1 | G5: {=XLOOKUP(C5,DimProductos[ID_Producto],DimProductos[[Producto]:[Precio_Lista]])} -> Laptop Gamer 16GB | H5: Laptops | I5: 14500 | J5: 22499 | K5: =F5*J5 -> 22499 | L5: =F5*I5 -> 14500 | M5: =IFS(E5="Tarjeta de Crédito",J5*Instrucciones!$J$2,E5<>"Tarjeta de Crédito",0) -> 0 | N5: =K5-L5-M5 -> 7999 | O5: =IF(N5>1500,"Ticket alto valor","Ticket Estandar") -> Ticket alto valor
A6: TK-8034 | B6: 2026-08-01 | C6: T-106 | D6: Sucursal Norte | E6: Tarjeta de Crédito | F6: 2 | G6: {=XLOOKUP(C6,DimProductos[ID_Producto],DimProductos[[Producto]:[Precio_Lista]])} -> Auriculares Noise Cancelling | H6: Audio | I6: 1600 | J6: 3199 | K6: =F6*J6 -> 6398 | L6: =F6*I6 -> 3200 | M6: =IFS(E6="Tarjeta de Crédito",J6*Instrucciones!$J$2,E6<>"Tarjeta de Crédito",0) -> 111.965 | N6: =K6-L6-M6 -> 3086.035 | O6: =IF(N6>1500,"Ticket alto valor","Ticket Estandar") -> Ticket alto valor
A7: TK-8160 | B7: 2026-08-01 | C7: T-102 | D7: Sucursal Poniente | E7: Efectivo | F7: 1 | G7: {=XLOOKUP(C7,DimProductos[ID_Producto],DimProductos[[Producto]:[Precio_Lista]])} -> Teclado Mecánico RGB | H7: Accesorios | I7: 650 | J7: 1350 | K7: =F7*J7 -> 1350 | L7: =F7*I7 -> 650 | M7: =IFS(E7="Tarjeta de Crédito",J7*Instrucciones!$J$2,E7<>"Tarjeta de Crédito",0) -> 0 | N7: =K7-L7-M7 -> 700 | O7: =IF(N7>1500,"Ticket alto valor","Ticket Estandar") -> Ticket Estandar
A8: TK-8168 | B8: 2026-08-01 | C8: T-106 | D8: Sucursal Norte | E8: Efectivo | F8: 1 | G8: {=XLOOKUP(C8,DimProductos[ID_Producto],DimProductos[[Producto]:[Precio_Lista]])} -> Auriculares Noise Cancelling | H8: Audio | I8: 1600 | J8: 3199 | K8: =F8*J8 -> 3199 | L8: =F8*I8 -> 1600 | M8: =IFS(E8="Tarjeta de Crédito",J8*Instrucciones!$J$2,E8<>"Tarjeta de Crédito",0) -> 0 | N8: =K8-L8-M8 -> 1599 | O8: =IF(N8>1500,"Ticket alto valor","Ticket Estandar") -> Ticket alto valor
A9: TK-8018 | B9: 2026-08-01 | C9: T-101 | D9: Sucursal Poniente | E9: Efectivo | F9: 1 | G9: {=XLOOKUP(C9,DimProductos[ID_Producto],DimProductos[[Producto]:[Precio_Lista]])} -> Monitor Curvo 27" | H9: Monitores | I9: 2800 | J9: 4999 | K9: =F9*J9 -> 4999 | L9: =F9*I9 -> 2800 | M9: =IFS(E9="Tarjeta de Crédito",J9*Instrucciones!$J$2,E9<>"Tarjeta de Crédito",0) -> 0 | N9: =K9-L9-M9 -> 2199 | O9: =IF(N9>1500,"Ticket alto valor","Ticket Estandar") -> Ticket alto valor
A10: TK-8186 | B10: 2026-08-01 | C10: T-102 | D10: Sucursal Norte | E10: Tarjeta de Débito | F10: 1 | G10: {=XLOOKUP(C10,DimProductos[ID_Producto],DimProductos[[Producto]:[Precio_Lista]])} -> Teclado Mecánico RGB | H10: Accesorios | I10: 650 | J10: 1350 | K10: =F10*J10 -> 1350 | L10: =F10*I10 -> 650 | M10: =IFS(E10="Tarjeta de Crédito",J10*Instrucciones!$J$2,E10<>"Tarjeta de Crédito",0) -> 0 | N10: =K10-L10-M10 -> 700 | O10: =IF(N10>1500,"Ticket alto valor","Ticket Estandar") -> Ticket Estandar
A11: TK-8094 | B11: 2026-08-01 | C11: T-108 | D11: Centro | E11: Transferencia | F11: 1 | G11: {=XLOOKUP(C11,DimProductos[ID_Producto],DimProductos[[Producto]:[Precio_Lista]])} -> Silla Ergonómica Pro | H11: Mobiliario | I11: 3200 | J11: 5699 | K11: =F11*J11 -> 5699 | L11: =F11*I11 -> 3200 | M11: =IFS(E11="Tarjeta de Crédito",J11*Instrucciones!$J$2,E11<>"Tarjeta de Crédito",0) -> 0 | N11: =K11-L11-M11 -> 2499 | O11: =IF(N11>1500,"Ticket alto valor","Ticket Estandar") -> Ticket alto valor
A12: TK-8005 | B12: 2026-08-01 | C12: T-108 | D12: Sucursal Sur | E12: Tarjeta de Crédito | F12: 1 | G12: {=XLOOKUP(C12,DimProductos[ID_Producto],DimProductos[[Producto]:[Precio_Lista]])} -> Silla Ergonómica Pro | H12: Mobiliario | I12: 3200 | J12: 5699 | K12: =F12*J12 -> 5699 | L12: =F12*I12 -> 3200 | M12: =IFS(E12="Tarjeta de Crédito",J12*Instrucciones!$J$2,E12<>"Tarjeta de Crédito",0) -> 199.465 | N12: =K12-L12-M12 -> 2299.535 | O12: =IF(N12>1500,"Ticket alto valor","Ticket Estandar") -> Ticket alto valor
A13: TK-8192 | B13: 2026-08-01 | C13: T-101 | D13: Sucursal Norte | E13: Tarjeta de Débito | F13: 2 | G13: {=XLOOKUP(C13,DimProductos[ID_Producto],DimProductos[[Producto]:[Precio_Lista]])} -> Monitor Curvo 27" | H13: Monitores | I13: 2800 | J13: 4999 | K13: =F13*J13 -> 9998 | L13: =F13*I13 -> 5600 | M13: =IFS(E13="Tarjeta de Crédito",J13*Instrucciones!$J$2,E13<>"Tarjeta de Crédito",0) -> 0 | N13: =K13-L13-M13 -> 4398 | O13: =IF(N13>1500,"Ticket alto valor","Ticket Estandar") -> Ticket alto valor
A14: TK-8087 | B14: 2026-08-02 | C14: T-105 | D14: Sucursal Sur | E14: Efectivo | F14: 1 | G14: {=XLOOKUP(C14,DimProductos[ID_Producto],DimProductos[[Producto]:[Precio_Lista]])} -> Laptop Ultrabook 14" | H14: Laptops | I14: 11200 | J14: 17999 | K14: =F14*J14 -> 17999 | L14: =F14*I14 -> 11200 | M14: =IFS(E14="Tarjeta de Crédito",J14*Instrucciones!$J$2,E14<>"Tarjeta de Crédito",0) -> 0 | N14: =K14-L14-M14 -> 6799 | O14: =IF(N14>1500,"Ticket alto valor","Ticket Estandar") -> Ticket alto valor
... A201: TK-8140 | B201: 2026-08-16 | C201: T-106 | D201: Sucursal Norte | E201: Efectivo | F201: 1 | G201: {=XLOOKUP(C201,DimProductos[ID_Producto],DimProductos[[Producto]:[Precio_Lista]])} -> Auriculares Noise Cancelling | H201: Audio | I201: 1600 | J201: 3199 | K201: =F201*J201 -> 3199 | L201: =F201*I201 -> 1600 | M201: =IFS(E201="Tarjeta de Crédito",J201*Instrucciones!$J$2,E201<>"Tarjeta de Crédito",0) -> 0 | N201: =K201-L201-M201 -> 1599 | O201: =IF(N201>1500,"Ticket alto valor","Ticket Estandar") -> Ticket alto valor

Sheet Tabla dinámica 1
